ftf_cli/__init__.py
ftf_cli/cli.py
ftf_cli/operations.py
ftf_cli/schema.py
ftf_cli/utils.py
ftf_cli/commands/__init__.py
ftf_cli/commands/add_import.py
ftf_cli/commands/add_input.py
ftf_cli/commands/add_variable.py
ftf_cli/commands/delete_module.py
ftf_cli/commands/expose_provider.py
ftf_cli/commands/generate_module.py
ftf_cli/commands/get_output_type_details.py
ftf_cli/commands/get_output_types.py
ftf_cli/commands/get_resources.py
ftf_cli/commands/login.py
ftf_cli/commands/preview_module.py
ftf_cli/commands/register_output_type.py
ftf_cli/commands/validate_directory.py
ftf_cli/commands/validate_facets.py
ftf_cli/commands/templates/__init__.py
ftf_cli/commands/templates/facets.yaml.j2
ftf_cli/commands/templates/main.tf.j2
ftf_cli/commands/templates/outputs.tf.j2
ftf_cli/commands/templates/variables.tf.j2
ftf_cli-0.3.5.dist-info/licenses/LICENSE.md
ftf_cli-0.3.5.dist-info/METADATA
ftf_cli-0.3.5.dist-info/WHEEL
ftf_cli-0.3.5.dist-info/entry_points.txt
ftf_cli-0.3.5.dist-info/top_level.txt
ftf_cli-0.3.5.dist-info/RECORD
