Metadata-Version: 2.4
Name: ftf-cli
Version: 0.3.5
Summary: Facets Terraform Cli
Author-email: Sanmesh Kakade <sanmesh.kakade@facets.cloud>
Project-URL: Homepage, https://github.com/Facets-cloud/module-development-cli
Project-URL: Repository, https://github.com/Facets-cloud/module-development-cli
Keywords: Facets,CLI,Terraform
Requires-Python: >=3.11
License-File: LICENSE.md
Requires-Dist: Click
Requires-Dist: Jinja2
Requires-Dist: PyYAML
Requires-Dist: checkov>=3.2.457
Requires-Dist: jsonschema
Requires-Dist: requests
Requires-Dist: questionary
Requires-Dist: facets-hcl
Requires-Dist: ruamel.yaml
Provides-Extra: dev
Requires-Dist: pytest>=8.3.5; extra == "dev"
Requires-Dist: pytest-mock; extra == "dev"
Requires-Dist: pyhcl>=0.4.5; extra == "dev"
Dynamic: license-file
